keyediffer/__init__.py
keyediffer/json_differ.py
keyediffer/models/__init__.py
keyediffer/models/diff_item.py
keyediffer/models/diff_path.py
keyediffer/models/diff_text.py
keyediffer/resources/__init__.py
keyediffer/resources/readme_tables.json
keyediffer/utils/__init__.py
keyediffer/utils/excel_utils.py
keyediffer/utils/helpers.py
keyediffer/utils/json_utils.py
cdisc_library_keyediffer-0.0.43.dist-info/METADATA
cdisc_library_keyediffer-0.0.43.dist-info/WHEEL
cdisc_library_keyediffer-0.0.43.dist-info/top_level.txt
cdisc_library_keyediffer-0.0.43.dist-info/RECORD
