Metadata-Version: 2.2
Name: cdisc-library-keyediffer
Version: 0.0.43
Summary: A library for diffing structured data, like json or xml files, where the two files being diffed share some common structure.
Author-email: Geraud Campion <gcampion@cdisc.org>
License: MIT
Project-URL: Repository, https://github.com/cdisc-org/cdisc-library-keyediffer
Requires-Python: >=3.12
Requires-Dist: genson
Requires-Dist: jsonpath-ng
Requires-Dist: jsonschema
Requires-Dist: requests
Requires-Dist: xlsxwriter
